{"id":"FH-0184","name":"Intentona Comunista","type":"historical_fact","subtype":"Batalha","description":"A Intentona Comunista foi uma insurreição de 1935 articulada por setores ligados à Aliança Nacional Libertadora e ao Partido Comunista, com levantes em cidades como Natal, Recife e Rio de Janeiro. Em Pernambuco, o episódio teve impacto político e repressivo, contribuindo para o endurecimento do Estado brasileiro nos anos seguintes. conecta-se a Carlos de Lima Cavalcanti e outros personagens da política local, permitindo compreender como conflitos ideológicos nacionais tiveram desdobramentos no Recife e em Pernambuco.","period":"","reference_location":"","municipality":"Pernambuco","neighborhood":"","image":"","aliases":[],"sources":[{"id":"FT-0001","title":"https://antonioaurel.github.io/data/data-visualization/recife-history-connections/pages/sources.html","source_type":"url","author":"","year":"","url":"https://antonioaurel.github.io/data/data-visualization/recife-history-connections/pages/sources.html","notes":""}],"edges":[{"target_id":"LC-0025","target_name":"Avenida 17 de Agosto","target_type":"place","type":"historical_event","strength":1},{"target_id":"FH-0488","target_name":"Batalha de Casa Forte","target_type":"historical_fact","type":"historical_event","strength":1},{"target_id":"FH-0049","target_name":"Batalha do Monte das Tabocas","target_type":"historical_fact","type":"historical_event","strength":1},{"target_id":"FH-0381","target_name":"Batalha dos Guararapes","target_type":"historical_fact","type":"historical_event","strength":1},{"target_id":"PE-AUS-0043","target_name":"Carlos de Lima Cavalcanti","target_type":"person","type":"person","strength":1},{"target_id":"LC-0435","target_name":"Casa-Museu Magdalena e Gilberto Freyre","target_type":"place","type":"historical_event","strength":1},{"target_id":"FH-0102","target_name":"Cruzeiro do Forte","target_type":"historical_fact","type":"historical_event","strength":1},{"target_id":"LC-0451","target_name":"Farol de Olinda","target_type":"place","type":"historical_event","strength":1},{"target_id":"LC-0135","target_name":"Fortaleza do Buraco","target_type":"place","type":"historical_event","strength":1},{"target_id":"LC-0136","target_name":"Forte das Cinco Pontas","target_type":"place","type":"historical_event","strength":1},{"target_id":"LC-0449","target_name":"Forte de São Francisco","target_type":"place","type":"historical_event","strength":1},{"target_id":"LC-0137","target_name":"Forte do Brum","target_type":"place","type":"historical_event","strength":1},{"target_id":"LC-0438","target_name":"Forte do Picão","target_type":"place","type":"historical_event","strength":1},{"target_id":"PE-AUS-0092","target_name":"Gregório Bezerra","target_type":"person","type":"person","strength":1},{"target_id":"FH-0153","target_name":"Guerra dos Mascates","target_type":"historical_fact","type":"historical_event","strength":1},{"target_id":"FH-0558","target_name":"Insurreição Pernambucana","target_type":"historical_fact","type":"historical_event","strength":1},{"target_id":"FH-0185","target_name":"Invasão Holandesa","target_type":"historical_fact","type":"historical_event","strength":1},{"target_id":"FH-0486","target_name":"Invasões Holandesas do Brasil","target_type":"historical_fact","type":"historical_event","strength":1},{"target_id":"LC-0388","target_name":"Maracatu Cruzeiro do Forte","target_type":"place","type":"historical_event","strength":1},{"target_id":"LC-0238","target_name":"Mural da Batalha dos Guararapes","target_type":"place","type":"historical_event","strength":1},{"target_id":"LC-0382","target_name":"Painel da Batalha dos Guararapes","target_type":"place","type":"historical_event","strength":1},{"target_id":"LC-0287","target_name":"Praça de Casa Forte","target_type":"place","type":"historical_event","strength":1},{"target_id":"FH-0304","target_name":"Revolução de 30","target_type":"historical_fact","type":"historical_event","strength":1},{"target_id":"LC-0349","target_name":"União Brasileira de Escritores","target_type":"place","type":"historical_event","strength":1}]}