{"id":"LC-0380","name":"Faculdade de Direito do Recife","type":"place","subtype":"Universidade","description":"A Faculdade de Direito do Recife é uma das instituições de ensino jurídico mais antigas e influentes do Brasil. Criada no século XIX, tornou-se centro de formação de juristas, políticos, escritores, jornalistas e intelectuais que marcaram a história brasileira. Sua presença consolidou o Recife como polo de debate jurídico, literário e político, especialmente por meio da chamada Escola do Recife. conecta-se a personagens como Joaquim Nabuco, Tobias Barreto, Castro Alves, Barbosa Lima Sobrinho e Álvaro Lins, formando um eixo intelectual fundamental.","period":"","reference_location":"Boa Vista","municipality":"Recife","neighborhood":"Boa Vista","image":"","aliases":[],"sources":[{"id":"FT-0001","title":"https://antonioaurel.github.io/data/data-visualization/recife-history-connections/pages/sources.html","source_type":"url","author":"","year":"","url":"https://antonioaurel.github.io/data/data-visualization/recife-history-connections/pages/sources.html","notes":""}],"edges":[{"target_id":"LC-0464","target_name":"Associação dos Ex-Combatentes do Brasil Seção de Pernambuco","target_type":"place","type":"local","strength":1},{"target_id":"PE-AUS-0021","target_name":"Augusto Lucena","target_type":"person","type":"person","strength":1},{"target_id":"LC-0026","target_name":"Avenida Agamenon Magalhães","target_type":"place","type":"local","strength":1},{"target_id":"LC-0035","target_name":"Avenida Mário Melo","target_type":"place","type":"local","strength":1},{"target_id":"LC-0039","target_name":"Avenida Visconde de Suassuna","target_type":"place","type":"local","strength":1},{"target_id":"LC-0043","target_name":"Banco do Nordeste","target_type":"place","type":"local","strength":1},{"target_id":"PE-AUS-0028","target_name":"Barbosa Lima Sobrinho","target_type":"person","type":"person","strength":1},{"target_id":"LC-0610","target_name":"Boa Vista","target_type":"place","type":"local","strength":1},{"target_id":"FH-0069","target_name":"Capitanias Hereditárias","target_type":"historical_fact","type":"local","strength":1},{"target_id":"PE-AUS-0057","target_name":"Demócrito de Souza Filho","target_type":"person","type":"manual","strength":1},{"target_id":"LC-0401","target_name":"Faculdade Maurício de Nassau","target_type":"place","type":"local","strength":1},{"target_id":"LC-0165","target_name":"Igreja da Capunga","target_type":"place","type":"local","strength":1},{"target_id":"PE-AUS-0108","target_name":"Joaquim Nabuco","target_type":"person","type":"person","strength":1},{"target_id":"PE-AUS-0120","target_name":"Manuel Correia de Andrade","target_type":"person","type":"person","strength":1},{"target_id":"PE-AUS-0126","target_name":"Mário Souto Maior","target_type":"person","type":"person","strength":1},{"target_id":"LC-0440","target_name":"Observatório do Alto da Sé","target_type":"place","type":"local","strength":1},{"target_id":"LC-0346","target_name":"UFPE","target_type":"place","type":"local","strength":1},{"target_id":"LC-0347","target_name":"UFRPE","target_type":"place","type":"local","strength":1},{"target_id":"LC-0605","target_name":"Universidade Católica de Pernambuco (Unicap)","target_type":"place","type":"local","strength":1},{"target_id":"PE-AUS-0007","target_name":"Álvaro Lins","target_type":"person","type":"person","strength":1}]}