{"id":"LC-0241","name":"Museu do Homem do Nordeste","type":"place","subtype":"Museu","description":"Museu do Homem do Nordeste é um museu localizado em Apipucos, no Recife/Pernambuco. O espaço se relaciona à formação cultural, educacional ou artística de Pernambuco e ajuda a preservar memórias, práticas e experiências coletivas. aparece associado a Museu Cais do Sertão, Instituto Ricardo Brennand, Oficina Brennand, Francisco Brennand e Museu do Homem do Nordeste, indicando sua função como registro de conhecimento, sociabilidade e produção cultural. o registro aproxima educação, patrimônio, cultura urbana e trajetórias históricas que atravessam a cidade.","period":"","reference_location":"Apipucos","municipality":"Recife","neighborhood":"Apipucos","image":"","aliases":[],"sources":[{"id":"FT-0001","title":"https://antonioaurel.github.io/data/data-visualization/recife-history-connections/pages/sources.html","source_type":"url","author":"","year":"","url":"https://antonioaurel.github.io/data/data-visualization/recife-history-connections/pages/sources.html","notes":""}],"edges":[{"target_id":"LC-0025","target_name":"Avenida 17 de Agosto","target_type":"place","type":"local","strength":1},{"target_id":"LC-0358","target_name":"Cais do Sertão","target_type":"place","type":"unresolved","strength":1},{"target_id":"LC-0075","target_name":"Casa da Cultura","target_type":"place","type":"local","strength":1},{"target_id":"LC-0453","target_name":"Casa dos Bonecos Gigantes do Alto da Sé","target_type":"place","type":"local","strength":1},{"target_id":"LC-0077","target_name":"Castelinho","target_type":"place","type":"local","strength":1},{"target_id":"LC-0121","target_name":"Estação Central","target_type":"place","type":"local","strength":1},{"target_id":"LC-0123","target_name":"Estação do Brum","target_type":"place","type":"local","strength":1},{"target_id":"PE-AUS-0080","target_name":"Francisco Brennand","target_type":"person","type":"person","strength":1},{"target_id":"LC-0146","target_name":"Fundação Joaquim Nabuco","target_type":"place","type":"local","strength":1},{"target_id":"LC-0129","target_name":"Fábrica Tacaruna","target_type":"place","type":"local","strength":1},{"target_id":"LC-0147","target_name":"Gabinete Português de Leitura","target_type":"place","type":"local","strength":1},{"target_id":"LC-0183","target_name":"Instituto Ricardo Brennand","target_type":"place","type":"local","strength":1},{"target_id":"LC-0433","target_name":"Mamam - Museu de Arte Moderna Aloísio Magalhães","target_type":"place","type":"local","strength":1},{"target_id":"LC-0223","target_name":"Memorial de Medicina","target_type":"place","type":"local","strength":1},{"target_id":"LC-0434","target_name":"Museu Franciscano de Arte Sacra","target_type":"place","type":"local","strength":1},{"target_id":"LC-0447","target_name":"Museu Regional de Olinda (MAC)","target_type":"place","type":"local","strength":1},{"target_id":"LC-0239","target_name":"Museu da Abolição (Casarão de João Alfredo)","target_type":"place","type":"local","strength":1},{"target_id":"LC-0240","target_name":"Museu do Estado","target_type":"place","type":"local","strength":1},{"target_id":"LC-0432","target_name":"Museum Murillo La Greca","target_type":"place","type":"local","strength":1},{"target_id":"LC-0248","target_name":"Oficina Brennand","target_type":"place","type":"local","strength":1},{"target_id":"LC-0337","target_name":"Teatro Apolo","target_type":"place","type":"local","strength":1},{"target_id":"LC-0344","target_name":"Torre Malakoff","target_type":"place","type":"local","strength":1},{"target_id":"LC-0343","target_name":"Torre do Zeppelin","target_type":"place","type":"local","strength":1}]}