{"id":"PE-AUS-0127","name":"Marquês de Olinda","type":"person","subtype":"Personagem","description":"O Marquês de Olinda, Pedro de Araújo Lima, foi estadista pernambucano e uma das figuras políticas mais importantes do Império. A Avenida Marquês de Olinda, no Recife Antigo, mantém seu nome em uma área marcada por comércio, porto e política.","period":"","reference_location":"Recife Antigo","municipality":"","neighborhood":"Recife Antigo","image":"","has_geo":false,"aliases":[],"sources":[{"id":"FT-0001","title":"https://antonioaurel.github.io/data/data-visualization/recife-history-connections/pages/sources.html","source_type":"url","author":"","year":"","url":"https://antonioaurel.github.io/data/data-visualization/recife-history-connections/pages/sources.html","notes":""}],"edges":[{"target_id":"LC-0036","target_name":"Avenida Marquês de Olinda","target_type":"place","type":"person","strength":1}]}