{"id":"PE-AUS-0133","name":"Mauro Mota","type":"personagem","subtype":"Personagem","description":"Mauro Mota foi poeta, jornalista e intelectual pernambucano. Suas conexões com o Restaurante Dom Pedro e o Savoy evocam o Recife dos encontros literários, da imprensa e da convivência cultural no centro da cidade.","de":"Mauro Mota was a Pernambuco poet, journalist and intellectual. His connections with the Restaurante Dom Pedro and the Savoy evoke the Recife of literary gatherings, the press and cultural life in the city centre.","period":"","reference_location":"Santo Antonio","municipality":"","neighborhood":"Santo Antonio","image":"","aliases":[],"sources":[{"id":"FT-0001","title":"https://antonioaurel.github.io/data/data-visualization/recife-history-connections/pages/sources.html","source_type":"url","author":"","year":"","url":"https://antonioaurel.github.io/data/data-visualization/recife-history-connections/pages/sources.html","notes":""}],"edges":[{"target_id":"LC-0302","target_name":"Restaurante Dom Pedro","target_type":"local","type":"person","strength":1},{"target_id":"LC-0328","target_name":"Savoy","target_type":"local","type":"person","strength":1}]}